{
"type": "FeatureCollection",
                                                                                
"features": [
{ "type": "Feature", "properties": { "TYPE": "MARINA", "NAME": "MARINA" }, "geometry": { "type": "Point", "coordinates": [ -7475820.9880359583, 2088514.9742915221 ] } },
{ "type": "Feature", "properties": { "TYPE": "MARINA", "NAME": "MARINA" }, "geometry": { "type": "Point", "coordinates": [ -7424216.8163946066, 2093596.258894607 ] } },
{ "type": "Feature", "properties": { "TYPE": "MARINA", "NAME": "MARINA" }, "geometry": { "type": "Point", "coordinates": [ -7424758.6654201485, 2093338.1576192419 ] } },
{ "type": "Feature", "properties": { "TYPE": "MARINA", "NAME": "MARINA" }, "geometry": { "type": "Point", "coordinates": [ -7409657.9013751997, 2094851.2063579229 ] } },
{ "type": "Feature", "properties": { "TYPE": "MARINA", "NAME": "SAN JUAN YACHT CLUB & MARINA" }, "geometry": { "type": "Point", "coordinates": [ -7356881.62724612, 2091350.3960943385 ] } },
{ "type": "Feature", "properties": { "TYPE": "MARINA", "NAME": "MARINA" }, "geometry": { "type": "Point", "coordinates": [ -7346251.6494217301, 2090915.4812013153 ] } },
{ "type": "Feature", "properties": { "TYPE": "MARINA", "NAME": "MARINA" }, "geometry": { "type": "Point", "coordinates": [ -7345058.3796627242, 2090660.9837230742 ] } },
{ "type": "Feature", "properties": { "TYPE": "MARINA", "NAME": "MARINA" }, "geometry": { "type": "Point", "coordinates": [ -7344733.0945047187, 2088638.3854427477 ] } },
{ "type": "Feature", "properties": { "TYPE": "MARINA", "NAME": "MARINA" }, "geometry": { "type": "Point", "coordinates": [ -7487342.5891561555, 2077963.1517341186 ] } },
{ "type": "Feature", "properties": { "TYPE": "MARINA", "NAME": "MARINA" }, "geometry": { "type": "Point", "coordinates": [ -7317731.8459700141, 2082227.3114043409 ] } },
{ "type": "Feature", "properties": { "TYPE": "MARINA", "NAME": "MARINA PUERTO CHICO" }, "geometry": { "type": "Point", "coordinates": [ -7306459.8264624914, 2078196.6041460268 ] } },
{ "type": "Feature", "properties": { "TYPE": "MARINA", "NAME": "VILLA MARINA YACHT HARBOR" }, "geometry": { "type": "Point", "coordinates": [ -7306767.2773816343, 2077707.4099031121 ] } },
{ "type": "Feature", "properties": { "TYPE": "MARINA", "NAME": "MARINA PUNTO REAL" }, "geometry": { "type": "Point", "coordinates": [ -7305868.7151549831, 2076679.1702695927 ] } },
{ "type": "Feature", "properties": { "TYPE": "MARINA", "NAME": "PUERTO DEL REY MARINA" }, "geometry": { "type": "Point", "coordinates": [ -7306261.1076844493, 2071185.2584509787 ] } },
{ "type": "Feature", "properties": { "TYPE": "MARINA", "NAME": "MARINA" }, "geometry": { "type": "Point", "coordinates": [ -7305541.7433690196, 2079402.7499547065 ] } },
{ "type": "Feature", "properties": { "TYPE": "MARINA", "NAME": "ISLETA MARINA" }, "geometry": { "type": "Point", "coordinates": [ -7304828.32884036, 2077318.8693849996 ] } },
{ "type": "Feature", "properties": { "TYPE": "MARINA", "NAME": "MARINA" }, "geometry": { "type": "Point", "coordinates": [ -7475743.660829166, 2062244.582016808 ] } },
{ "type": "Feature", "properties": { "TYPE": "MARINA", "NAME": "MARINA" }, "geometry": { "type": "Point", "coordinates": [ -7305635.1664852705, 2064863.2420769716 ] } },
{ "type": "Feature", "properties": { "TYPE": "MARINA", "NAME": "MARINA" }, "geometry": { "type": "Point", "coordinates": [ -7314837.3532724176, 2059177.4338320151 ] } },
{ "type": "Feature", "properties": { "TYPE": "MARINA", "NAME": "MARINA" }, "geometry": { "type": "Point", "coordinates": [ -7479581.7343567973, 2046006.0549276825 ] } },
{ "type": "Feature", "properties": { "TYPE": "MARINA", "NAME": "MARINA" }, "geometry": { "type": "Point", "coordinates": [ -7478543.8633754663, 2040858.1948403546 ] } },
{ "type": "Feature", "properties": { "TYPE": "MARINA", "NAME": "MARINA" }, "geometry": { "type": "Point", "coordinates": [ -7477664.8013474718, 2038752.1216320579 ] } },
{ "type": "Feature", "properties": { "TYPE": "MARINA", "NAME": "CLUB NAUTICO DE BOQUERON" }, "geometry": { "type": "Point", "coordinates": [ -7477946.7932832548, 2040478.3944977452 ] } },
{ "type": "Feature", "properties": { "TYPE": "MARINA", "NAME": "MARINA" }, "geometry": { "type": "Point", "coordinates": [ -7477709.8258132786, 2040334.8364638512 ] } },
{ "type": "Feature", "properties": { "TYPE": "MARINA", "NAME": "CLUB DE PORTIVO OESTE" }, "geometry": { "type": "Point", "coordinates": [ -7479552.8540107217, 2049393.641215059 ] } },
{ "type": "Feature", "properties": { "TYPE": "MARINA", "NAME": "MARINA" }, "geometry": { "type": "Point", "coordinates": [ -7324758.9027691623, 2046750.8393978048 ] } },
{ "type": "Feature", "properties": { "TYPE": "MARINA", "NAME": "MARINA PALMAS DEL MAR" }, "geometry": { "type": "Point", "coordinates": [ -7324494.7612154838, 2046671.7725903757 ] } },
{ "type": "Feature", "properties": { "TYPE": "MARINA", "NAME": "MARINA" }, "geometry": { "type": "Point", "coordinates": [ -7463853.326216911, 2034376.1664992871 ] } },
{ "type": "Feature", "properties": { "TYPE": "MARINA", "NAME": "MARINA" }, "geometry": { "type": "Point", "coordinates": [ -7465117.1011673743, 2034600.9277026628 ] } },
{ "type": "Feature", "properties": { "TYPE": "MARINA", "NAME": "CLUB NAUTICO LA PARGUERA" }, "geometry": { "type": "Point", "coordinates": [ -7462671.932092946, 2034141.8036875871 ] } },
{ "type": "Feature", "properties": { "TYPE": "MARINA", "NAME": "MARINA" }, "geometry": { "type": "Point", "coordinates": [ -7418765.0876745638, 2035358.2126981711 ] } },
{ "type": "Feature", "properties": { "TYPE": "MARINA", "NAME": "PONCE YACHT AND FISHING CLUB" }, "geometry": { "type": "Point", "coordinates": [ -7416564.514706498, 2035306.4224861483 ] } },
{ "type": "Feature", "properties": { "TYPE": "MARINA", "NAME": "MARINA" }, "geometry": { "type": "Point", "coordinates": [ -7416071.0656003645, 2033715.1586201214 ] } },
{ "type": "Feature", "properties": { "TYPE": "MARINA", "NAME": "MARINA" }, "geometry": { "type": "Point", "coordinates": [ -7415787.3912711376, 2033380.8026150027 ] } },
{ "type": "Feature", "properties": { "TYPE": "MARINA", "NAME": "OLD CLUB NAUTICO" }, "geometry": { "type": "Point", "coordinates": [ -7392386.2682249555, 2032064.9280105405 ] } },
{ "type": "Feature", "properties": { "TYPE": "MARINA", "NAME": "CLUB NAUTICO DE SANTA ISABEL" }, "geometry": { "type": "Point", "coordinates": [ -7391841.0184269538, 2031938.605295067 ] } },
{ "type": "Feature", "properties": { "TYPE": "MARINA", "NAME": "MARINA" }, "geometry": { "type": "Point", "coordinates": [ -7379963.4069895782, 2033010.5738066798 ] } },
{ "type": "Feature", "properties": { "TYPE": "MARINA", "NAME": "MARINA" }, "geometry": { "type": "Point", "coordinates": [ -7379892.0670706313, 2032529.5906184174 ] } },
{ "type": "Feature", "properties": { "TYPE": "MARINA", "NAME": "NAUTICO DE GUAYAMA" }, "geometry": { "type": "Point", "coordinates": [ -7369527.9023431167, 2030685.9107114372 ] } },
{ "type": "Feature", "properties": { "TYPE": "MARINA", "NAME": "MARINA PASEO LAS AMERICAS" }, "geometry": { "type": "Point", "coordinates": [ -7354328.5536515666, 2033063.6806103915 ] } }
]
}
